_g_api.cp312-win32.pyd
_g_api_can.cp312-win32.pyd
_g_api_common.cp312-win32.pyd
_g_api_diag.cp312-win32.pyd
_g_api_net2run.cp312-win32.pyd
goe_api/__init__.py
goe_api/g_api.py
goe_api/g_api_can.py
goe_api/g_api_can_wrap.c
goe_api/g_api_common.py
goe_api/g_api_common_wrap.c
goe_api/g_api_diag.py
goe_api/g_api_diag_wrap.c
goe_api/g_api_net2run.py
goe_api/g_api_net2run_wrap.c
goe_api/g_api_wrap.c
goe_api-0.1.0.dist-info/LICENCE
goe_api-0.1.0.dist-info/METADATA
goe_api-0.1.0.dist-info/WHEEL
goe_api-0.1.0.dist-info/top_level.txt
goe_api-0.1.0.dist-info/RECORD
