Metadata-Version: 2.1
Name: goe_api
Version: 0.1.0
Summary: python wrapper to interact with g-api driver
Author-email: Philip Pastrik <develop@pastrik.com>
License-File: LICENCE
